src/__init__.py
src/double.py
pystdlib-0.0.3.dist-info/LICENSE
pystdlib-0.0.3.dist-info/METADATA
pystdlib-0.0.3.dist-info/WHEEL
pystdlib-0.0.3.dist-info/top_level.txt
pystdlib-0.0.3.dist-info/RECORD
