Metadata-Version: 2.1
Name: pystdlib
Version: 0.0.3
Summary: A custom standard library module for Python
Home-page: https://github.com/disoft-io/pystdlib/tree/main
Author: Disoft
Author-email: ciccabr9@gmail.com
Classifier: Programming Language :: Python :: 3
Classifier: Operating System :: OS Independent
Requires-Python: >=3.6
License-File: LICENSE
